{
    "personaId": "87654321",
    "nombreYApellidos": "Juan Antonio Pérez",
    "tipoMora": "Avanzada",
    "productos": {
        "cantidadProductos": 1,
        "detalleProductos": [
            {
                "nombreProducto": "Préstamo Personal",
                "diasAtraso": 20,
                "saldoAbonar": "300.000"
            }
        ]
    },
    "Es Prome": "SI",
    "TipoAcuerdo": "Refinanciación",
    "fechaVencimientoAcuerdo": "20-12-2025",
    "montoAcuerdo": "500.000",
    "cartera": "Consumo",
    "judicializable": "No"
}